release/__init__.py
release/sign-launcher.py
release/sign-tag.py
release/update_manpages.py
release/util.py
repo/__init__.py
repo/color.py
repo/command.py
repo/editor.py
repo/error.py
repo/event_log.py
repo/fetch.py
repo/git_command.py
repo/git_config.py
repo/git_refs.py
repo/git_ssh
repo/git_superproject.py
repo/git_trace2_event_log.py
repo/gitc_utils.py
repo/hooks.py
repo/main.py
repo/manifest_xml.py
repo/pager.py
repo/platform_utils.py
repo/platform_utils_win32.py
repo/progress.py
repo/project.py
repo/pyversion.py
repo/repo_dir.py
repo/ssh.py
repo/trace.py
repo/wrapper.py
repo/hooks/__init__.py
repo/hooks/commit-msg
repo/hooks/pre-auto-gc
repo/subcmds/__init__.py
repo/subcmds/abandon.py
repo/subcmds/branches.py
repo/subcmds/checkout.py
repo/subcmds/cherry_pick.py
repo/subcmds/diff.py
repo/subcmds/diffmanifests.py
repo/subcmds/download.py
repo/subcmds/forall.py
repo/subcmds/gitc_delete.py
repo/subcmds/gitc_init.py
repo/subcmds/grep.py
repo/subcmds/help.py
repo/subcmds/info.py
repo/subcmds/init.py
repo/subcmds/list.py
repo/subcmds/manifest.py
repo/subcmds/overview.py
repo/subcmds/prune.py
repo/subcmds/rebase.py
repo/subcmds/smartsync.py
repo/subcmds/stage.py
repo/subcmds/start.py
repo/subcmds/status.py
repo/subcmds/sync.py
repo/subcmds/upload.py
repo/subcmds/version.py
gitrepo-2.32.2.dist-info/LICENSE
gitrepo-2.32.2.dist-info/METADATA
gitrepo-2.32.2.dist-info/WHEEL
gitrepo-2.32.2.dist-info/entry_points.txt
gitrepo-2.32.2.dist-info/top_level.txt
gitrepo-2.32.2.dist-info/RECORD
