Metadata-Version: 2.1
Name: gitrepo
Version: 2.32.2
Summary: Repo helps manage many Git repositories
Home-page: https://gerrit.googlesource.com/git-repo/
Maintainer: Various
Maintainer-email: repo-discuss@googlegroups.com
License: Apache
Project-URL: Bug Tracker, https://bugs.chromium.org/p/gerrit/issues/list?q=component:Applications%3Erepo
Keywords: git repo android workflow
Classifier: Development Status :: 6 - Mature
Classifier: Environment :: Console
Classifier: Intended Audience :: Developers
Classifier: License :: OSI Approved :: Apache Software License
Classifier: Natural Language :: English
Classifier: Operating System :: MacOS :: MacOS X
Classifier: Operating System :: Microsoft :: Windows :: Windows 10
Classifier: Operating System :: POSIX :: Linux
Classifier: Operating System :: POSIX :: Linux
Classifier: Programming Language :: Python :: 3
Classifier: Programming Language :: Python :: 3 :: Only
Classifier: Topic :: Software Development :: Version Control :: Git
Requires-Python: >=3.6
License-File: LICENSE
